LICENSE
MANIFEST.in
README.md
setup.cfg
setup.py
snapi_py_client/__init__.py
snapi_py_client/api_client.py
snapi_py_client/configuration.py
snapi_py_client/rest.py
snapi_py_client/snapi_bridge.py
stocknotebridgenew.egg-info/PKG-INFO
stocknotebridgenew.egg-info/SOURCES.txt
stocknotebridgenew.egg-info/dependency_links.txt
stocknotebridgenew.egg-info/requires.txt
stocknotebridgenew.egg-info/top_level.txt