Metadata-Version: 2.1
Name: stocknotebridgenew
Version: 5.0.5
Summary: official python library for Stocknote APIs
Home-page: https://github.com/samco-sdk/Python-SDK
Author: Samco Securities Limited
Author-email: apisupport@samco.in
License: MIT License
Keywords: stocknote api,stocknote python sdk,samco api trading,samco algo trading,stock markets samco
Platform: UNKNOWN
Classifier: Intended Audience :: Developers
Classifier: Natural Language :: English
Classifier: Operating System :: OS Independent
Classifier: Programming Language :: Python
Classifier: Programming Language :: Python :: 2
Classifier: Programming Language :: Python :: 3
Classifier: Programming Language :: Python :: Implementation :: PyPy
Classifier: Topic :: Software Development :: Libraries :: Python Modules
License-File: LICENSE
